Metadata-Version: 2.1
Name: windML
Version: 0.3.8
Summary: WindML
Home-page: UNKNOWN
Author: Mohammed Terry-Jack
Author-email: <mohammedterryjack@gmail.com>
License: UNKNOWN
Keywords: python,extreme learning machine,direct feedback alignment,matrix factorisation,ml,machine learning,rnn,transformer,numpy,lite
Platform: UNKNOWN
Classifier: Development Status :: 1 - Planning
Classifier: Intended Audience :: Developers
Classifier: Programming Language :: Python :: 3
Classifier: Operating System :: MacOS :: MacOS X
Requires-Dist: numpy
